writracker/__init__.py
writracker/commonio.py
writracker/uiutil.py
writracker/utils.py
writracker/encoder/__init__.py
writracker/encoder/dataio.py
writracker/encoder/expcoder.py
writracker/encoder/manip.py
writracker/encoder/transform.py
writracker/encoder/trialcoder.py
writracker/plotter/__init__.py
writracker/plotter/plotter.py
writracker/recorder/__init__.py
writracker/recorder/dataio.py
writracker/recorder/recorder.py
writracker/recorder/results.py
writracker/recorder/wintab.py
writracker/recorder/wintab_params.py
writracker-1.0.2.dist-info/LICENSE.txt
writracker-1.0.2.dist-info/METADATA
writracker-1.0.2.dist-info/WHEEL
writracker-1.0.2.dist-info/top_level.txt
writracker-1.0.2.dist-info/RECORD
