Metadata-Version: 2.1
Name: writracker
Version: 1.0.2
Summary: Framework for pen-tracking experiments
Home-page: http://www.mathinklab.com/writracker
Author: Dror Dotan
Author-email: dotandro@mail.tau.ac.il
License: GPL
Platform: UNKNOWN
Classifier: Development Status :: 4 - Beta
Classifier: Intended Audience :: Science/Research
Classifier: Topic :: Scientific/Engineering
Classifier: Programming Language :: Python :: 3.7
Requires-Dist: numpy
Requires-Dist: matplotlib
Requires-Dist: tk
Requires-Dist: PySimpleGUI
Requires-Dist: pandas
Requires-Dist: PyQt5
Requires-Dist: mutagen
Requires-Dist: pygame
Requires-Dist: pywin32
Requires-Dist: pyautogui
